[
  {
    "ID": "123456780",
    "First": "Simi",
    "Last": "Goldfinger",
    "LMP": "2022-11-30",
    "DOB": "1989-01-01"
  },
  {
    "ID": "123456781",
    "First": "chava",
    "Last": "druker",
    "LMP": "2022-12-13",
    "DOB": "1983-03-12"
  },
  {
    "ID": "123456782",
    "First": "Gal",
    "Last": "Zadik",
    "LMP": "2022-07-29",
    "DOB": "1987-05-17"
  },
  {
    "ID": "123456783",
    "First": "Dalia",
    "Last": "Tsim",
    "LMP": "2022-12-18",
    "DOB": "1989-05-14"
  },
  {
    "ID": "123456784",
    "First": "dora",
    "Last": "struma",
    "LMP": "2022-06-03",
    "DOB": "1994-07-12"
  },
  {
    "ID": "123456785",
    "First": "Sivan",
    "Last": "Luka",
    "LMP": "2022-07-26",
    "DOB": "1998-12-19"
  },
  {
    "ID": "123456786",
    "First": "Mor",
    "Last": "Zula",
    "LMP": "2022-09-17",
    "DOB": "1997-09-10"
  },
  {
    "ID": "123456787",
    "First": "Chaya",
    "Last": "Zilbershmit",
    "LMP": "2022-09-09",
    "DOB": "2001-12-23"
  },
  {
    "ID": "345678987",
    "First": "Malka",
    "Last": "Cohen",
    "LMP": "2022-06-29",
    "DOB": "2002-05-28"
  },
  {
    "ID": "321345432",
    "First": "Emeli",
    "Last": "Zarka",
    "LMP": "2022-08-17",
    "DOB": "2003-04-13"
  },
  {
    "ID": "376578934",
    "First": "Hagit",
    "Last": "Zimmer",
    "LMP": "2022-09-30",
    "DOB": "1989-02-28"
  },
  {
    "ID": "921234321",
    "First": "Haleli",
    "Last": "Bukobza",
    "LMP": "2022-10-13",
    "DOB": "1989-03-29"
  },
  {
    "ID": "874123543",
    "First": "Neta",
    "Last": "Shayer",
    "LMP": "2022-10-29",
    "DOB": "2000-02-01"
  },
  {
    "ID": "786543123",
    "First": "Niva",
    "Last": "Haldenkratz",
    "LMP": "2022-11-18",
    "DOB": "1987-02-01"
  },
  {
    "ID": "543678432",
    "First": "Esther",
    "Last": "Zajac",
    "LMP": "2022-10-03",
    "DOB": "1999-01-03"
  },
  {
    "ID": "321432543",
    "First": "Zoya",
    "Last": "Pomerantz",
    "LMP": "2022-09-26",
    "DOB": "1987-09-27"
  },
  {
    "ID": "215345632",
    "First": "Zeeva",
    "Last": "Tarnegolet",
    "LMP": "2022-09-17",
    "DOB": "1986-01-12"
  },
  {
    "ID": "876956345",
    "First": "Zila",
    "Last": "Bakenbaeur",
    "LMP": "2022-09-09",
    "DOB": "1990-11-13"
  },
  {
    "ID": "987876765",
    "First": "Korin",
    "Last": "Kalestasz",
    "LMP": "2022-08-29",
    "DOB": "2000-02-26"
  },
  {
    "ID": "345765987",
    "First": "Nina",
    "Last": "Simone",
    "LMP": "2022-08-17",
    "DOB": "1993-09-17"
  }
]
